{
    "version": "1.5.0-beta8",
    "description": "Open source voice labeling application",
    "homepage": "https://github.com/sdercolin/vlabeler/",
    "license": "Apache-2.0",
    "architecture": {
        "64bit": {
            "url": "https://github.com/sdercolin/vlabeler/releases/download/1.5.0-beta8/vlabeler-1.5.0-beta8-win64.zip",
            "hash": "67320a2b258388dd5eb05db40dc9f447667f64022b61b31b4f8726f978b7b038"
        }
    },
    "bin": "vLabeler.exe",
    "shortcuts": [
        [
            "vLabeler.exe",
            "vLabeler"
        ]
    ],
    "checkver": {
        "url": "https://github.com/sdercolin/vlabeler/releases",
        "regex": "tag/([\\d.]+-[a-z\\d]+)"
    },
    "autoupdate": {
        "architecture": {
            "64bit": {
                "url": "https://github.com/sdercolin/vlabeler/releases/download/$version/vlabeler-$version-win64.zip"
            }
        }
    }
}
